Metadata-Version: 2.1
Name: rave-python3
Version: 1.4.0
Summary: Python library for Flutterwave for Business (F4B) v2 APIs.
Home-page: https://github.com/Forchapeatl/Python-v3
Author: Flutterwave
Author-email: developers@flutterwavego.com
License: MIT
Classifier: Programming Language :: Python :: 2
Classifier: Programming Language :: Python :: 2.7
Classifier: Programming Language :: Python :: 3
Classifier: Programming Language :: Python :: 3.5
Classifier: Programming Language :: Python :: 3.6
Classifier: Programming Language :: Python :: 3.7
Classifier: Programming Language :: Python :: 3.8
Classifier: License :: OSI Approved :: MIT License
Classifier: Operating System :: OS Independent
Requires-Python: >=2.7, !=3.0.*, !=3.1.*, !=3.2.*, !=3.3.*, !=3.4.*
License-File: LICENSE
Requires-Dist: pycryptodome
Requires-Dist: requests
